excel_serializer/__init__.py
django_excel_serializer-2.0.1.dist-info/LICENSE
django_excel_serializer-2.0.1.dist-info/METADATA
django_excel_serializer-2.0.1.dist-info/WHEEL
django_excel_serializer-2.0.1.dist-info/top_level.txt
django_excel_serializer-2.0.1.dist-info/RECORD
